lynxkite_core/__init__.py
lynxkite_core/executors/__init__.py
lynxkite_core/executors/one_by_one.py
lynxkite_core/executors/simple.py
lynxkite_core/ops.py
lynxkite_core/workspace.py
lynxkite_core-0.3.0.dist-info/WHEEL
lynxkite_core-0.3.0.dist-info/METADATA
lynxkite_core-0.3.0.dist-info/RECORD
