Metadata-Version: 2.3
Name: lynxkite-core
Version: 0.3.0
Summary: A lightweight dependency for authoring LynxKite operations and executors
Classifier: License :: OSI Approved :: GNU Affero General Public License v3 or later (AGPLv3+)
Requires-Dist: pydantic>=2.11.7
Requires-Python: >=3.11
Project-URL: Homepage, https://github.com/lynxkite/lynxkite-2000/
